ktools/__init__.py
ktools-0.1.14.dist-info/DESCRIPTION.rst
ktools-0.1.14.dist-info/METADATA
ktools-0.1.14.dist-info/RECORD
ktools-0.1.14.dist-info/WHEEL
ktools-0.1.14.dist-info/metadata.json
ktools-0.1.14.dist-info/top_level.txt
tests/__init__.py
tests/test_sample.py
