Metadata-Version: 2.0
Name: ktools
Version: 0.1.14
Summary: kirin's toolkit.
Home-page: https://github.com/fx-kirin/ktools
Author: fx-kirin
Author-email: ono.kirin@gmail.com
License: UNKNOWN
Platform: UNKNOWN
Classifier: Development Status :: 2 - Pre-Alpha
Classifier: Programming Language :: Python
Classifier: Programming Language :: Python :: 2
Classifier: Programming Language :: Python :: 2.7
Classifier: Programming Language :: Python :: 3
Classifier: Programming Language :: Python :: 3.4
Classifier: Programming Language :: Python :: 3.5
